Metadata-Version: 2.1
Name: kivy-garden.ebs.marquee
Version: 3.0
Summary: Marquee text widget for Kivy
Home-page: https://github.com/ebs-universe/kivy_garden.ebs.marquee
Author: Chintalagiri Shashank
Author-email: shashank.chintalagiri@gmail.com
Project-URL: Bug Reports, https://github.com/ebs-universe/kivy_garden.ebs.marquee/issues
Project-URL: Source, https://github.com/ebs-universe/kivy_garden.ebs.marquee
Keywords: Kivy kivy-garden
Classifier: Development Status :: 4 - Beta
Classifier: Intended Audience :: Developers
Classifier: Topic :: Software Development :: Libraries
Classifier: License :: OSI Approved :: MIT License
Classifier: Programming Language :: Python :: 3.5
Classifier: Programming Language :: Python :: 3.6
Classifier: Programming Language :: Python :: 3.7
Classifier: Programming Language :: Python :: 3.8
Classifier: Programming Language :: Python :: 3.9
Classifier: Programming Language :: Python :: 3.10
Provides-Extra: dev
Provides-Extra: ci
License-File: LICENSE.txt
License-File: AUTHORS.txt
